src/componentes.v
`timescale 1 ns / 10 ps
module registro4 (input wire [3:0] entrada, input wire bit_en_desp, input wire Carga, Desplaza, clk, reset, output wire [3:0] salida);
	//Registro de 4 bits, soporta Carga de entrada, reseteo y desplazamiento aritmético o lógico
	// La línea de Carga indica que se va a asignar un nuevo valor al registro que viene por "entrada"
	// La línea de Desplaza indica que se va a desplazar el contenido del registro. El bit más significativo se completa con la entrada "bit_en_desp"
	wire enable;

	assign enable = Carga | Desplaza; //Si se carga o desplaza se habilitan en modificación los biestables
	cdaff ff0(Carga, entrada[0], salida[1], clk, reset, enable, salida[0]);
	cdaff ff1(Carga, entrada[1], salida[2], clk, reset, enable, salida[1]);
	cdaff ff2(Carga, entrada[2], salida[3], clk, reset, enable, salida[2]);
	cdaff ff3(Carga, entrada[3], bit_en_desp, clk, reset, enable, salida[3]); //entra un bit en el desplaz
endmodule

module registro3 (input wire [2:0] entrada, input wire bit_en_desp, input wire Carga, Desplaza, clk, reset, output wire [2:0] salida);
	//Registro de 3 bits, soporta Carga de entrada, reseteo y desplazamiento aritmético o lógico
	// La línea de Carga indica que se va a asignar un nuevo valor al registro que viene por "entrada"
	// La línea de Desplaza indica que se va a desplazar el contenido del registro. El bit más significativo se completa con la entrada "bit_en_desp"
	wire enable;

	assign enable = Carga | Desplaza; //Si se carga o desplaza se habilitan en modificación los biestables
	cdaff ff0(Carga, entrada[0], salida[1], clk, reset, enable, salida[0]);
	cdaff ff1(Carga, entrada[1], salida[2], clk, reset, enable, salida[1]);
	cdaff ff2(Carga, entrada[2], bit_en_desp, clk, reset, enable, salida[2]); //entra un bit en el desplaz
endmodule

//Biestable con entrada de mux para aceptar dos entradas posibles
module cdaff (input wire selc_d, inp_c, inp_d, clk, reset, carga, output wire salida);
	wire inp;
	
	ffdc ff0(clk, reset, carga, inp, salida);
	mux2_1_i1 mux0(inp, inp_d, inp_c, selc_d);
endmodule

//Mux de dos entradas de 1 bit realizado a partir de puertas 
module mux2_1_i1(output wire out, input wire a, b, s);
	//Declaración de conexiones internas
	wire  s_n, sa, sb;	   
	//Instancias de puertas y sus conexiones
	not inv1 (s_n, s);
	and and1 (sa, a, s_n);
	and and2 (sb, b, s);
	or or1 (out, sa, sb);
endmodule

module ffdc #(parameter retardo = 1)(input wire clk, reset, carga, d, output reg q);
	//reset asíncrono, carga síncrona
	always @(posedge clk, posedge reset)
	  if (reset)
		q <= 1'b0; //asignación no bloqueante q=0
	  else
		if (carga)
		  q <= d; //asignación no bloqueante q=d
endmodule

module sum_resta4(output wire[3:0] S, output wire c_out, input wire[3:0] A, input wire[3:0] B, input wire resta);
	assign {c_out, S} = (resta == 1) ? A - B : A + B;
endmodule

src/uc.v
//vim: set syntax=verilog
`timescale 1 ns / 10 ps
module unidad_control(input wire start, clk, input wire [2:0] q, output wire fin, shift, suma, init, loadA);

reg [3:0] currentstate, nextstate;

//Parameters
parameter S0 = 4'b0000;  ///>
parameter S1 = 4'b0001;
parameter S2 = 4'b0010;
parameter S3 = 4'b0011;
parameter S4 = 4'b0100;
parameter S5 = 4'b0101;
parameter S6 = 4'b0110;
parameter S7 = 4'b0111;
parameter S8 = 4'b1000;
parameter S9 = 4'b1001;
parameter S10 = 4'b1010;
parameter S11 = 4'b1011;
parameter S12 = 4'b1100;
parameter S13 = 4'b1101;
parameter S14 = 4'b1110;

parameter S15 = 4'b1110;
parameter S16 = 4'b1111;
//parameter Reset = 4'b1111;

always @ (posedge clk, posedge start)
begin
	if (start)
	begin
		currentstate <= S0;
	end
	else
		currentstate <= nextstate;
end


always @ (*)
	case (currentstate)

		S0: 
			if (q[1])
				nextstate = S1;
			else
				nextstate = S2;

		S1:
			nextstate = S2;

		S2:
			if ((~q[2] & q[1]) | (q[2] & ~q[1]))
				nextstate = S3;
			else
				nextstate = S4;
		S3:
			nextstate = S4;

		S4:
			if ((~q[2] & q[1]) | (q[2] & ~q[1]))
				nextstate = S5;
			else
				nextstate = S6;

		S5:
			nextstate = S6;

		S6:
			nextstate = S7;

		S7:
			nextstate = S7;

		default:
			nextstate = S0;
		endcase


		assign init = (currentstate == (S0)) ? 1:0;
		assign shift = (currentstate == S2 | currentstate == S4 | currentstate == S6) ? 1:0;
		assign loadA = (currentstate == S1| currentstate == S3 | currentstate == S5) ? 1:0;
		assign suma = (~q[1] & q[0]) ? 1:0;
		assign fin = (currentstate == S7) ? 1:0;

endmodule

src/datapath.v
//vim: set syntax=verilog
`timescale 1 ns / 10 ps
`include "componentes.v"

module cd (input wire clk, reset, shift_uc, sum_uc, init_uc, loadA_uc, input wire [2:0] Q_uc, M_uc, output wire [2:0] q_uc, output wire [5:0] result);

wire ground, SalidaQ_1, Carry, Resta;
wire [3:0] SalSum, SalidaA, SalidaM, M_4b;
wire [3:0] SalidaQ;
wire [3:0] a_in, q_in;
wire a_carry_in;

assign M_4b = {M_uc[2], M_uc};
assign ground = 1'b0;
assign Resta = ~sum_uc;
assign q_carry_in = loadA_uc ? SalSum[0] : SalidaA[0];

registro4 A ({SalSum[3], SalSum[3:1]}, SalidaA[3], loadA_uc, shift_uc, clk, reset, SalidaA);
registro4 Q ({Q_uc, 1'b0}, q_carry_in, init_uc, (shift_uc | loadA_uc), clk, reset, SalidaQ);
registro4 M (M_4b, ground, init_uc, ground, clk, reset, SalidaM);

sum_resta4 sumador(SalSum, Carry, SalidaA, SalidaM, Resta);

assign q_uc = SalidaQ[2:0];
assign result = {SalidaA[2:0], SalidaQ[3:1]};

endmodule

src/mult.v
`timescale 1 ns / 10	ps
`include "datapath.v"
`include "uc.v"

module mult (input wire[2:0] M_mult, Q_mult, input wire clk, start_mul, output wire[5:0] Result_mul, output wire fin);

wire shift, sum, init, loadA, reset;
wire [2:0] q, q_uc;

assign q_uc = init ? {Q_mult[1:0], 1'b0} : q;

cd camino_datos ( clk, start_mul, shift, sum, init, loadA, Q_mult, M_mult, q, Result_mul);
unidad_control uc ( start_mul, clk, q_uc, fin, shift, sum, init, loadA );

endmodule

src/multiplicador_tb.v
`timescale 1 ns / 10 ps
`include "mult.v"
module multiplicador_tb;
//Recordar que el caso de -4 en tres bits en el multiplicando dará error en Booth si no hacemos que los registros A y M tengan un bit más (hay overflow) (depende de la implementación del sumador/restador)
parameter NUM_BITS = 3;
parameter NUM_TESTS = (2**(2*NUM_BITS));
parameter MAX_RANGE = (2**(NUM_BITS-1))-1;
parameter MIN_RANGE = - (2**(NUM_BITS-1));

integer contador;
reg clk, reset;
wire Fin;

reg signed [NUM_BITS-1:0] multiplicador;
reg signed [NUM_BITS-1:0] multiplicando;
wire [(2*NUM_BITS)-1:0] resultado;
reg signed [(2*NUM_BITS)-1:0] resultado_esperado;

// generación de reloj clk
always //siempre activo, no hay condición de activación
begin
  clk = 1'b0;
  #5;
  clk = 1'b1;
  #5;
end

// Módulo a probar
mult circuito_multiplicador(multiplicando, multiplicador, clk, reset, resultado, Fin);

initial
begin
  $dumpfile("multiplicador_tb.vcd");
  $dumpvars;
  #10000   //Evita ejecución infinita
  $finish;
end

//Preparación caso inicial
initial
begin
  multiplicando = MIN_RANGE;
  multiplicador = MIN_RANGE;
  contador = 1;
end 

initial
begin
  reset = 1'b1;
  #1;
  reset = 1'b0;
end

always @(posedge Fin)
begin
  resultado_esperado = multiplicador * multiplicando;
  //Comprobación de resultados
  $write("%d x %d = %d", multiplicando, multiplicador, resultado_esperado);
  if (resultado !== resultado_esperado)
    $display("\tERROR    Obtenido=%b", resultado);
  else
    $display("\tCORRECTO Obtenido=%b", resultado);
  
  #20  //tiempo de espera entre una multiplicación y la siguiente
  if (contador == NUM_TESTS)
    $finish;
  else //Siguiente caso
  begin
    contador = contador + 1;
    if (multiplicador == MAX_RANGE)
    begin
      multiplicador = MIN_RANGE;
      multiplicando = multiplicando + 1;
    end
    else
    begin
      multiplicador = multiplicador + 1;
    end
    reset= 1'b1;
    #1;
    reset= 1'b0;           
  end
end

endmodule

src/multiplicador_tb.vcd
$date
	Tue Feb 23 18:04:32 2021
$end
$version
	Icarus Verilog
$end
$timescale
	10ps
$end
$scope module multiplicador_tb $end
$var wire 6 ! resultado [5:0] $end
$var wire 1 " Fin $end
$var reg 1 # clk $end
$var reg 3 $ multiplicador [2:0] $end
$var reg 3 % multiplicando [2:0] $end
$var reg 1 & reset $end
$var reg 6 ' resultado_esperado [5:0] $end
$var integer 32 ( contador [31:0] $end
$scope module circuito_multiplicador $end
$var wire 3 ) M_mult [2:0] $end
$var wire 3 * Q_mult [2:0] $end
$var wire 1 # clk $end
$var wire 1 & start_mul $end
$var wire 1 + sum $end
$var wire 1 , shift $end
$var wire 3 - q_uc [2:0] $end
$var wire 3 . q [2:0] $end
$var wire 1 / loadA $end
$var wire 1 0 init $end
$var wire 1 " fin $end
$var wire 6 1 Result_mul [5:0] $end
$scope module camino_datos $end
$var wire 3 2 M_uc [2:0] $end
$var wire 3 3 Q_uc [2:0] $end
$var wire 1 4 Resta $end
$var wire 1 # clk $end
$var wire 1 5 ground $end
$var wire 1 & reset $end
$var wire 1 + sum_uc $end
$var wire 1 , shift_uc $end
$var wire 6 6 result [5:0] $end
$var wire 3 7 q_uc [2:0] $end
$var wire 1 / loadA_uc $end
$var wire 1 0 init_uc $end
$var wire 4 8 SalidaQ [3:0] $end
$var wire 4 9 SalidaM [3:0] $end
$var wire 4 : SalidaA [3:0] $end
$var wire 4 ; SalSum [3:0] $end
$var wire 4 < M_4b [3:0] $end
$var wire 1 = Carry $end
$scope module A $end
$var wire 1 > bit_en_desp $end
$var wire 1 # clk $end
$var wire 1 ? enable $end
$var wire 1 & reset $end
$var wire 4 @ salida [3:0] $end
$var wire 4 A entrada [3:0] $end
$var wire 1 , Desplaza $end
$var wire 1 / Carga $end
$scope module ff0 $end
$var wire 1 ? carga $end
$var wire 1 # clk $end
$var wire 1 B inp_c $end
$var wire 1 C inp_d $end
$var wire 1 & reset $end
$var wire 1 / selc_d $end
$var wire 1 D salida $end
$var wire 1 E inp $end
$scope module ff0 $end
$var wire 1 ? carga $end
$var wire 1 # clk $end
$var wire 1 & reset $end
$var wire 1 E d $end
$var reg 1 D q $end
$upscope $end
$scope module mux0 $end
$var wire 1 C a $end
$var wire 1 B b $end
$var wire 1 E out $end
$var wire 1 F s_n $end
$var wire 1 G sa $end
$var wire 1 H sb $end
$var wire 1 / s $end
$upscope $end
$upscope $end
$scope module ff1 $end
$var wire 1 ? carga $end
$var wire 1 # clk $end
$var wire 1 I inp_c $end
$var wire 1 J inp_d $end
$var wire 1 & reset $end
$var wire 1 / selc_d $end
$var wire 1 K salida $end
$var wire 1 L inp $end
$scope module ff0 $end
$var wire 1 ? carga $end
$var wire 1 # clk $end
$var wire 1 & reset $end
$var wire 1 L d $end
$var reg 1 K q $end
$upscope $end
$scope module mux0 $end
$var wire 1 J a $end
$var wire 1 I b $end
$var wire 1 L out $end
$var wire 1 M s_n $end
$var wire 1 N sa $end
$var wire 1 O sb $end
$var wire 1 / s $end
$upscope $end
$upscope $end
$scope module ff2 $end
$var wire 1 ? carga $end
$var wire 1 # clk $end
$var wire 1 P inp_c $end
$var wire 1 Q inp_d $end
$var wire 1 & reset $end
$var wire 1 / selc_d $end
$var wire 1 R salida $end
$var wire 1 S inp $end
$scope module ff0 $end
$var wire 1 ? carga $end
$var wire 1 # clk $end
$var wire 1 & reset $end
$var wire 1 S d $end
$var reg 1 R q $end
$upscope $end
$scope module mux0 $end
$var wire 1 Q a $end
$var wire 1 P b $end
$var wire 1 S out $end
$var wire 1 T s_n $end
$var wire 1 U sa $end
$var wire 1 V sb $end
$var wire 1 / s $end
$upscope $end
$upscope $end
$scope module ff3 $end
$var wire 1 ? carga $end
$var wire 1 # clk $end
$var wire 1 W inp_c $end
$var wire 1 > inp_d $end
$var wire 1 & reset $end
$var wire 1 / selc_d $end
$var wire 1 X salida $end
$var wire 1 Y inp $end
$scope module ff0 $end
$var wire 1 ? carga $end
$var wire 1 # clk $end
$var wire 1 & reset $end
$var wire 1 Y d $end
$var reg 1 X q $end
$upscope $end
$scope module mux0 $end
$var wire 1 > a $end
$var wire 1 W b $end
$var wire 1 Y out $end
$var wire 1 Z s_n $end
$var wire 1 [ sa $end
$var wire 1 \ sb $end
$var wire 1 / s $end
$upscope $end
$upscope $end
$upscope $end
$scope module M $end
$var wire 1 5 Desplaza $end
$var wire 1 5 bit_en_desp $end
$var wire 1 # clk $end
$var wire 1 ] enable $end
$var wire 4 ^ entrada [3:0] $end
$var wire 1 & reset $end
$var wire 4 _ salida [3:0] $end
$var wire 1 0 Carga $end
$scope module ff0 $end
$var wire 1 ] carga $end
$var wire 1 # clk $end
$var wire 1 ` inp_c $end
$var wire 1 a inp_d $end
$var wire 1 & reset $end
$var wire 1 0 selc_d $end
$var wire 1 b salida $end
$var wire 1 c inp $end
$scope module ff0 $end
$var wire 1 ] carga $end
$var wire 1 # clk $end
$var wire 1 & reset $end
$var wire 1 c d $end
$var reg 1 b q $end
$upscope $end
$scope module mux0 $end
$var wire 1 a a $end
$var wire 1 ` b $end
$var wire 1 c out $end
$var wire 1 d s_n $end
$var wire 1 e sa $end
$var wire 1 f sb $end
$var wire 1 0 s $end
$upscope $end
$upscope $end
$scope module ff1 $end
$var wire 1 ] carga $end
$var wire 1 # clk $end
$var wire 1 g inp_c $end
$var wire 1 h inp_d $end
$var wire 1 & reset $end
$var wire 1 0 selc_d $end
$var wire 1 i salida $end
$var wire 1 j inp $end
$scope module ff0 $end
$var wire 1 ] carga $end
$var wire 1 # clk $end
$var wire 1 & reset $end
$var wire 1 j d $end
$var reg 1 i q $end
$upscope $end
$scope module mux0 $end
$var wire 1 h a $end
$var wire 1 g b $end
$var wire 1 j out $end
$var wire 1 k s_n $end
$var wire 1 l sa $end
$var wire 1 m sb $end
$var wire 1 0 s $end
$upscope $end
$upscope $end
$scope module ff2 $end
$var wire 1 ] carga $end
$var wire 1 # clk $end
$var wire 1 n inp_c $end
$var wire 1 o inp_d $end
$var wire 1 & reset $end
$var wire 1 0 selc_d $end
$var wire 1 p salida $end
$var wire 1 q inp $end
$scope module ff0 $end
$var wire 1 ] carga $end
$var wire 1 # clk $end
$var wire 1 & reset $end
$var wire 1 q d $end
$var reg 1 p q $end
$upscope $end
$scope module mux0 $end
$var wire 1 o a $end
$var wire 1 n b $end
$var wire 1 q out $end
$var wire 1 r s_n $end
$var wire 1 s sa $end
$var wire 1 t sb $end
$var wire 1 0 s $end
$upscope $end
$upscope $end
$scope module ff3 $end
$var wire 1 ] carga $end
$var wire 1 # clk $end
$var wire 1 u inp_c $end
$var wire 1 5 inp_d $end
$var wire 1 & reset $end
$var wire 1 0 selc_d $end
$var wire 1 v salida $end
$var wire 1 w inp $end
$scope module ff0 $end
$var wire 1 ] carga $end
$var wire 1 # clk $end
$var wire 1 & reset $end
$var wire 1 w d $end
$var reg 1 v q $end
$upscope $end
$scope module mux0 $end
$var wire 1 5 a $end
$var wire 1 u b $end
$var wire 1 w out $end
$var wire 1 x s_n $end
$var wire 1 y sa $end
$var wire 1 z sb $end
$var wire 1 0 s $end
$upscope $end
$upscope $end
$upscope $end
$scope module Q $end
$var wire 1 { bit_en_desp $end
$var wire 1 # clk $end
$var wire 1 | enable $end
$var wire 4 } entrada [3:0] $end
$var wire 1 & reset $end
$var wire 4 ~ salida [3:0] $end
$var wire 1 , Desplaza $end
$var wire 1 0 Carga $end
$scope module ff0 $end
$var wire 1 | carga $end
$var wire 1 # clk $end
$var wire 1 !" inp_c $end
$var wire 1 "" inp_d $end
$var wire 1 & reset $end
$var wire 1 0 selc_d $end
$var wire 1 #" salida $end
$var wire 1 $" inp $end
$scope module ff0 $end
$var wire 1 | carga $end
$var wire 1 # clk $end
$var wire 1 & reset $end
$var wire 1 $" d $end
$var reg 1 #" q $end
$upscope $end
$scope module mux0 $end
$var wire 1 "" a $end
$var wire 1 !" b $end
$var wire 1 $" out $end
$var wire 1 %" s_n $end
$var wire 1 &" sa $end
$var wire 1 '" sb $end
$var wire 1 0 s $end
$upscope $end
$upscope $end
$scope module ff1 $end
$var wire 1 | carga $end
$var wire 1 # clk $end
$var wire 1 (" inp_c $end
$var wire 1 )" inp_d $end
$var wire 1 & reset $end
$var wire 1 0 selc_d $end
$var wire 1 *" salida $end
$var wire 1 +" inp $end
$scope module ff0 $end
$var wire 1 | carga $end
$var wire 1 # clk $end
$var wire 1 & reset $end
$var wire 1 +" d $end
$var reg 1 *" q $end
$upscope $end
$scope module mux0 $end
$var wire 1 )" a $end
$var wire 1 (" b $end
$var wire 1 +" out $end
$var wire 1 ," s_n $end
$var wire 1 -" sa $end
$var wire 1 ." sb $end
$var wire 1 0 s $end
$upscope $end
$upscope $end
$scope module ff2 $end
$var wire 1 | carga $end
$var wire 1 # clk $end
$var wire 1 /" inp_c $end
$var wire 1 0" inp_d $end
$var wire 1 & reset $end
$var wire 1 0 selc_d $end
$var wire 1 1" salida $end
$var wire 1 2" inp $end
$scope module ff0 $end
$var wire 1 | carga $end
$var wire 1 # clk $end
$var wire 1 & reset $end
$var wire 1 2" d $end
$var reg 1 1" q $end
$upscope $end
$scope module mux0 $end
$var wire 1 0" a $end
$var wire 1 /" b $end
$var wire 1 2" out $end
$var wire 1 3" s_n $end
$var wire 1 4" sa $end
$var wire 1 5" sb $end
$var wire 1 0 s $end
$upscope $end
$upscope $end
$scope module ff3 $end
$var wire 1 | carga $end
$var wire 1 # clk $end
$var wire 1 6" inp_c $end
$var wire 1 { inp_d $end
$var wire 1 & reset $end
$var wire 1 0 selc_d $end
$var wire 1 7" salida $end
$var wire 1 8" inp $end
$scope module ff0 $end
$var wire 1 | carga $end
$var wire 1 # clk $end
$var wire 1 & reset $end
$var wire 1 8" d $end
$var reg 1 7" q $end
$upscope $end
$scope module mux0 $end
$var wire 1 { a $end
$var wire 1 6" b $end
$var wire 1 8" out $end
$var wire 1 9" s_n $end
$var wire 1 :" sa $end
$var wire 1 ;" sb $end
$var wire 1 0 s $end
$upscope $end
$upscope $end
$upscope $end
$scope module sumador $end
$var wire 4 <" A [3:0] $end
$var wire 4 =" B [3:0] $end
$var wire 1 4 resta $end
$var wire 1 = c_out $end
$var wire 4 >" S [3:0] $end
$upscope $end
$upscope $end
$scope module uc $end
$var wire 1 # clk $end
$var wire 3 ?" q [2:0] $end
$var wire 1 & start $end
$var wire 1 + suma $end
$var wire 1 , shift $end
$var wire 1 / loadA $end
$var wire 1 0 init $end
$var wire 1 " fin $end
$var reg 4 @" currentstate [3:0] $end
$var reg 4 A" nextstate [3:0] $end
$upscope $end
$upscope $end
$upscope $end
$scope module registro3 $end
$var wire 1 B" Carga $end
$var wire 1 C" Desplaza $end
$var wire 1 D" bit_en_desp $end
$var wire 1 E" clk $end
$var wire 1 F" enable $end
$var wire 3 G" entrada [2:0] $end
$var wire 1 H" reset $end
$var wire 3 I" salida [2:0] $end
$scope module ff0 $end
$var wire 1 F" carga $end
$var wire 1 E" clk $end
$var wire 1 J" inp_c $end
$var wire 1 K" inp_d $end
$var wire 1 H" reset $end
$var wire 1 B" selc_d $end
$var wire 1 L" salida $end
$var wire 1 M" inp $end
$scope module ff0 $end
$var wire 1 F" carga $end
$var wire 1 E" clk $end
$var wire 1 H" reset $end
$var wire 1 M" d $end
$var reg 1 L" q $end
$upscope $end
$scope module mux0 $end
$var wire 1 K" a $end
$var wire 1 J" b $end
$var wire 1 M" out $end
$var wire 1 B" s $end
$var wire 1 N" s_n $end
$var wire 1 O" sa $end
$var wire 1 P" sb $end
$upscope $end
$upscope $end
$scope module ff1 $end
$var wire 1 F" carga $end
$var wire 1 E" clk $end
$var wire 1 Q" inp_c $end
$var wire 1 R" inp_d $end
$var wire 1 H" reset $end
$var wire 1 B" selc_d $end
$var wire 1 S" salida $end
$var wire 1 T" inp $end
$scope module ff0 $end
$var wire 1 F" carga $end
$var wire 1 E" clk $end
$var wire 1 H" reset $end
$var wire 1 T" d $end
$var reg 1 S" q $end
$upscope $end
$scope module mux0 $end
$var wire 1 R" a $end
$var wire 1 Q" b $end
$var wire 1 T" out $end
$var wire 1 B" s $end
$var wire 1 U" s_n $end
$var wire 1 V" sa $end
$var wire 1 W" sb $end
$upscope $end
$upscope $end
$scope module ff2 $end
$var wire 1 F" carga $end
$var wire 1 E" clk $end
$var wire 1 X" inp_c $end
$var wire 1 D" inp_d $end
$var wire 1 H" reset $end
$var wire 1 B" selc_d $end
$var wire 1 Y" salida $end
$var wire 1 Z" inp $end
$scope module ff0 $end
$var wire 1 F" carga $end
$var wire 1 E" clk $end
$var wire 1 H" reset $end
$var wire 1 Z" d $end
$var reg 1 Y" q $end
$upscope $end
$scope module mux0 $end
$var wire 1 D" a $end
$var wire 1 X" b $end
$var wire 1 Z" out $end
$var wire 1 B" s $end
$var wire 1 [" s_n $end
$var wire 1 \" sa $end
$var wire 1 ]" sb $end
$upscope $end
$upscope $end
$upscope $end
$enddefinitions $end
#0
$dumpvars
x]"
x\"
z["
xZ"
xY"
zX"
xW"
xV"
zU"
xT"
xS"
xR"
zQ"
xP"
xO"
zN"
xM"
xL"
xK"
zJ"
bx I"
zH"
bz G"
xF"
zE"
zD"
zC"
zB"
b10 A"
b0 @"
b0 ?"
b0 >"
b0 ="
b0 <"
1;"
0:"
09"
18"
07"
16"
05"
04"
03"
02"
01"
00"
0/"
0."
0-"
0,"
0+"
0*"
0)"
0("
0'"
0&"
0%"
0$"
0#"
0""
0!"
b0 ~
b1000 }
1|
0{
1z
0y
0x
1w
0v
1u
1t
0s
0r
1q
0p
0o
1n
0m
0l
0k
0j
0i
0h
0g
0f
0e
0d
0c
0b
0a
0`
b0 _
b1100 ^
1]
0\
0[
1Z
0Y
0X
0W
0V
0U
1T
0S
0R
0Q
0P
0O
0N
1M
0L
0K
0J
0I
0H
0G
1F
0E
0D
0C
0B
b0 A
b0 @
0?
0>
0=
b1100 <
b0 ;
b0 :
b0 9
b0 8
b0 7
b0 6
05
14
b100 3
b100 2
b0 1
10
0/
b0 .
b0 -
0,
0+
b100 *
b100 )
b1 (
bx '
1&
b100 %
b100 $
0#
0"
b0 !
$end
#100
0&
#500
12"
1j
1?
08"
14"
0w
1s
1l
1,
0;"
19"
13"
1,"
1%"
1|
0z
1x
0t
1r
1k
1d
0]
1P
00
b100 ;
b100 A
b100 >"
1=
b100 A"
1o
1h
10"
b100 !
b100 1
b100 6
b10 @"
1v
b1100 9
b1100 _
b1100 ="
1p
b1000 8
b1000 ~
17"
1#
#1000
0#
#1500
1+"
02"
1-"
b100 -
b100 ?"
04"
1)"
b100 .
b100 7
00"
b10 !
b10 1
b10 6
b101 A"
11"
b100 8
b100 ~
07"
b100 @"
1#
#2000
0#
#2500
0|
1S
0,
0Z
1V
0T
0M
0F
1/
0+"
1$"
0-"
1&"
b10 -
b10 ?"
b110 A"
0)"
1""
b1 !
b1 1
b1 6
b10 .
b10 7
b101 @"
01"
b10 8
b10 ~
1*"
1#
#3000
0#
#3500
1L
0S
1N
1|
1Z
0V
1T
1M
1F
1W
0P
1,
0/
b1000 ;
b1000 A
b1000 >"
1J
b100001 !
b100001 1
b100001 6
b111 A"
b100 :
b100 @
b100 <"
1R
b110 @"
1#
#4000
0#
#4500
0=
04
1+
0|
0?
0,
b10000 '
0$"
0L
1W
1P
1I
1E
1"
0&"
b1 -
b1 ?"
0N
b1110 ;
b1110 A
b1110 >"
1G
0""
b1 .
b1 7
0J
1C
b10000 !
b10000 1
b10000 6
b111 @"
0*"
b1 8
b1 ~
1#"
0R
b10 :
b10 @
b10 <"
1K
1#
#5000
0#
#5500
1#
#6000
0#
#6500
14
0+
18"
1+"
1w
1;"
09"
03"
1."
0,"
0%"
1|
1z
0x
1t
0r
0k
0d
1]
1q
0j
0W
0P
0I
0E
10
0"
0s
0l
b10 -
b10 ?"
b0 ;
b0 A
b0 >"
0G
b1 A"
0o
0h
b0 .
b0 7
0C
b0 !
b0 1
b0 6
b0 @"
0v
b0 9
b0 _
b0 ="
0p
b0 8
b0 ~
0#"
b0 :
b0 @
b0 <"
0K
1("
1#
1&
b1010 }
b101 $
b101 *
b101 3
b10 (
#6600
0&
#7000
0#
#7500
1S
12"
1$"
1j
0Z
0T
0M
0F
1?
1V
08"
14"
0+"
1&"
0w
1s
1l
1/
1P
0;"
19"
13"
0."
1,"
1%"
0|
0z
1x
0t
1r
1k
1d
0]
b100 ;
b100 A
b100 >"
1=
00
1""
b10 .
b10 7
10"
b101 !
b101 1
b101 6
1h
1o
b10 A"
1*"
b1010 8
b1010 ~
17"
1p
b1100 9
b1100 _
b1100 ="
1v
b1 @"
1#
#8000
0#
#8500
1L
1N
1|
1Z
1T
1M
1F
0Y
0S
1,
0/
0\
0V
1W
0P
b1000 ;
b1000 A
b1000 >"
b11 A"
1J
b100101 !
b100101 1
b100101 6
b10 @"
b100 :
b100 @
b100 <"
1R
1#
#9000
0#
#9500
1Y
1\
0=
04
1+
1S
0|
0Z
0T
0M
0F
1V
1O
0,
1/
0E
1W
1P
1I
1L
0$"
1+"
02"
0G
b1110 ;
b1110 A
b1110 >"
0N
0&"
1-"
b101 -
b101 ?"
04"
1C
0J
0""
1)"
b101 .
b101 7
00"
b10010 !
b10010 1
b10010 6
b100 A"
1K
b10 :
b10 @
b10 <"
0R
1#"
0*"
11"
b101 8
b101 ~
07"
b11 @"
1#
#10000
0#
#10500
1E
1[
1U
1N
1G
1|
0\
1Z
1T
0O
1M
1F
1S
1,
0/
0V
0P
b1010 ;
b1010 A
b1010 >"
1=
b101 A"
1Q
1>
1J
b110010 !
b110010 1
b110010 6
b100 @"
1X
b1110 :
b1110 @
b1110 <"
1R
1#
#11000
0#
#11500
0Y
0W
0=
14
0+
0S
0|
0[
0U
0N
0G
0,
0\
0Z
0T
1O
0M
1H
0F
1B
18"
1$"
0+"
1/
b11 ;
b11 A
b11 >"
1:"
1&"
0-"
b10 -
b10 ?"
1{
1""
0)"
b111001 !
b111001 1
b111001 6
b10 .
b10 7
b110 A"
b1111 :
b1111 @
b1111 <"
1D
0#"
1*"
b10 8
b10 ~
01"
b101 @"
1#
#12000
0#
#12500
0L
1G
1|
1Z
1T
0O
1M
0H
1F
1,
0/
1P
b111 ;
b111 A
b111 >"
1=
b111 A"
0Q
0>
0J
b11001 !
b11001 1
b11001 6
b110 @"
0X
b11 :
b11 @
b11 <"
0R
1#
#13000
0#
#13500
1W
0=
04
1+
0|
0?
0I
0E
0$"
12"
0,
b1100 '
b1101 ;
b1101 A
b1101 >"
0G
0&"
b1 -
b1 ?"
14"
1"
0C
0""
b1 .
b1 7
10"
b1100 !
b1100 1
b1100 6
b1 :
b1 @
b1 <"
0K
1#"
0*"
b1001 8
b1001 ~
17"
b111 @"
1#
#14000
0#
#14500
1#
#15000
0#
#15500
14
0+
1w
0j
0W
0P
0B
1;"
09"
15"
03"
0,"
0%"
1|
1z
0x
1t
0r
0k
0d
1]
0:"
b100 -
b100 ?"
04"
0l
b0 ;
b0 A
b0 >"
0s
10
0"
0{
b0 .
b0 7
00"
b0 !
b0 1
b0 6
0h
0o
b10 A"
b0 :
b0 @
b0 <"
0D
0#"
b0 8
b0 ~
07"
0p
b0 9
b0 _
b0 ="
0v
b0 @"
0("
1/"
1#
1&
b1100 }
b110 $
b110 *
b110 3
b11 (
#15600
0&
#16000
0#
#16500
1+"
1j
1?
08"
14"
1-"
0w
1s
1l
1,
0;"
19"
05"
13"
1,"
1%"
1|
0z
1x
0t
1r
1k
1d
0]
1P
00
b100 ;
b100 A
b100 >"
1=
b11 A"
1o
1h
10"
1)"
b110 !
b110 1
b110 6
b100 .
b100 7
b10 @"
1v
b1100 9
b1100 _
b1100 ="
1p
17"
b1100 8
b1100 ~
11"
1#
#17000
0#
#17500
1S
0|
0Z
1V
0T
0M
0F
0,
1/
1$"
02"
1&"
b110 -
b110 ?"
04"
1""
b110 .
b110 7
00"
b11 !
b11 1
b11 6
b100 A"
1*"
b110 8
b110 ~
07"
b11 @"
1#
#18000
0#
#18500
1L
1N
1|
1Z
1T
1M
1F
0Y
0S
1,
0/
0\
0V
1W
0P
b1000 ;
b1000 A
b1000 >"
b110 A"
1J
b100011 !
b100011 1
b100011 6
b100 @"
b100 :
b100 @
b100 <"
1R
1#
#19000
0#
#19500
1E
0W
1P
1I
0L
0+"
1G
b110 ;
b110 A
b110 >"
0N
0-"
b11 -
b11 ?"
1C
0J
0)"
b10001 !
b10001 1
b10001 6
b11 .
b11 7
b111 A"
1K
b10 :
b10 @
b10 <"
0R
1#"
b11 8
b11 ~
01"
b110 @"
1#
#20000
0#
#20500
1W
0=
04
1+
0|
0?
0,
b1000 '
0$"
0E
0I
1B
18"
1"
0&"
b1 -
b1 ?"
0G
b1101 ;
b1101 A
b1101 >"
1:"
0""
b1 .
b1 7
0C
b1000 !
b1000 1
b1000 6
1{
b111 @"
b1 8
b1 ~
0*"
0K
b1 :
b1 @
b1 <"
1D
1#
#21000
0#
#21500
1#
#22000
0#
#22500
14
0+
12"
1+"
1w
1;"
09"
15"
03"
1."
0,"
0%"
1|
1z
0x
1t
0r
0k
0d
1]
1q
0j
0W
0P
0B
18"
10
0"
0s
0l
b110 -
b110 ?"
b0 ;
b0 A
b0 >"
0:"
b1 A"
0o
0h
b0 .
b0 7
b0 !
b0 1
b0 6
0{
b0 @"
0v
b0 9
b0 _
b0 ="
0p
b0 8
b0 ~
0#"
b0 :
b0 @
b0 <"
0D
1("
1#
1&
b1110 }
b111 $
b111 *
b111 3
b100 (
#22600
0&
#23000
0#
